{
  "players": [
    {
      "name": "Lionel Messi",
      "age": "33",
      "year": "1987",
      "team": "FC Barcelona",
      "nacionality": "Argentina"
    },
    {
      "name": "Cristiano Ronaldo",
      "age": "35",
      "year": "1985",
      "team": "Juventus",
      "nacionality": "Portugal"
    },
    {
      "name": "Neymar Jr",
      "age": "28",
      "year": "1992",
      "team": "Paris Saint-Germain",
      "nacionality": "Brazil"
    },
    {
      "name": "Kylian Mbappé",
      "age": "21",
      "year": "1998",
      "team": "Paris Saint-Germain",
      "nacionality": "France"
    },
    {
      "name": "Robert Lewandowski",
      "age": "32",
      "year": "1988",
      "team": "Bayern Munich",
      "nacionality": "Poland"
    },
    {
      "name": "Kevin De Bruyne",
      "age": "29",
      "year": "1991",
      "team": "Manchester City",
      "nacionality": "Belgium"
    },
    {
      "name": "Sergio Ramos",
      "age": "34",
      "year": "1986",
      "team": "Real Madrid",
      "nacionality": "Spain"
    },
    {
      "name": "Virgil van Dijk",
      "age": "29",
      "year": "1991",
      "team": "Liverpool",
      "nacionality": "Netherlands"
    },
    {
      "name": "Sadio Mané",
      "age": "28",
      "year": "1992",
      "team": "Liverpool",
      "nacionality": "Senegal"
    },
    {
      "name": "Mohamed Salah",
      "age": "28",
      "year": "1992",
      "team": "Liverpool",
      "nacionality": "Egypt"
    },
    {
      "name": "Harry Kane",
      "age": "27",
      "year": "1993",
      "team": "Tottenham Hotspur",
      "nacionality": "England"
    },
    {
      "name": "Eden Hazard",
      "age": "29",
      "year": "1991",
      "team": "Real Madrid",
      "nacionality": "Belgium"
    },
    {
      "name": "Antoine Griezmann",
      "age": "29",
      "year": "1991",
      "team": "Barcelona",
      "nacionality": "France"
    },
    {
      "name": "Luka Modrić",
      "age": "35",
      "year": "1985",
      "team": "Real Madrid",
      "nacionality": "Croatia"
    },
    {
      "name": "Paul Pogba",
      "age": "27",
      "year": "1993",
      "team": "Manchester United",
      "nacionality": "France"
    },
    {
      "name": "Toni Kroos",
      "age": "30",
      "year": "1990",
      "team": "Real Madrid",
      "nacionality": "Germany"
    },
    {
      "name": "Manuel Neuer",
      "age": "34",
      "year": "1986",
      "team": "Bayern Munich",
      "nacionality": "Germany"
    },
    {
      "name": "Sergio Agüero",
      "age": "32",
      "year": "1988",
      "team": "Manchester City",
      "nacionality": "Argentina"
    },
    {
      "name": "Karim Benzema",
      "age": "33",
      "year": "1987",
      "team": "Real Madrid",
      "nacionality": "France"
    }
  ]
}